sceneprogdatasets/__init__.py
sceneprogdatasets/retriever.py
sceneprogdatasets/futurehssd/__init__.py
sceneprogdatasets/futurehssd/futurehssd.py
sceneprogdatasets/objaverse/__init__.py
sceneprogdatasets/objaverse/objaverse.py
sceneprogdatasets-0.1.8.dist-info/METADATA
sceneprogdatasets-0.1.8.dist-info/WHEEL
sceneprogdatasets-0.1.8.dist-info/top_level.txt
sceneprogdatasets-0.1.8.dist-info/RECORD
