Metadata-Version: 2.4
Name: sceneprogdatasets
Version: 0.1.8
Summary: A dataset retriever for SceneProg project
Home-page: https://github.com/KunalMGupta/sceneprogdatasets.git
Author: Kunal Gupta
Author-email: k5gupta@ucsd.edu
Classifier: Programming Language :: Python :: 3
Classifier: License :: OSI Approved :: MIT License
Classifier: Operating System :: OS Independent
Requires-Python: >=3.9
Requires-Dist: sceneprogllm
Requires-Dist: scipy
Requires-Dist: trimesh
Dynamic: author
Dynamic: author-email
Dynamic: classifier
Dynamic: description
Dynamic: description-content-type
Dynamic: home-page
Dynamic: requires-dist
Dynamic: requires-python
Dynamic: summary
